{
  "$schema": "https://ui.shadcn.com/schema/registry-item.json",
  "name": "plus-sign",
  "title": "plus-sign",
  "description": "Animated plus sign icon",
  "dependencies": [
    "motion"
  ],
  "files": [
    {
      "path": "icons/plus-sign.tsx",
      "content": "'use client';\n\nimport type { Variants } from 'motion/react';\nimport { motion, useAnimation } from 'motion/react';\nimport type { HTMLAttributes } from 'react';\nimport { forwardRef, useCallback, useImperativeHandle, useRef } from 'react';\nimport { cn } from '@/lib/utils';\n\nexport interface PlusSignIconHandle {\n  startAnimation: () => void;\n  stopAnimation: () => void;\n}\n\ninterface PlusSignIconProps extends HTMLAttributes<HTMLDivElement> {\n  size?: number;\n}\n\n// a quarter turn with momentum and a swell — something is being added\nconst svgVariants: Variants = {\n  normal: {\n    rotate: 0,\n    scale: 1,\n    transition: { type: 'spring', duration: 0.5, bounce: 0.15 },\n  },\n  animate: {\n    rotate: 90,\n    scale: [1, 1.15, 1],\n    transition: {\n      rotate: { type: 'spring', duration: 0.5, bounce: 0.25 },\n      scale: { duration: 0.45, times: [0, 0.4, 1], ease: 'easeInOut' },\n    },\n  },\n};\n\nconst PlusSignIcon = forwardRef<PlusSignIconHandle, PlusSignIconProps>(\n  ({ onMouseEnter, onMouseLeave, className, size = 28, ...props }, ref) => {\n    const controls = useAnimation();\n    const isControlledRef = useRef(false);\n\n    useImperativeHandle(ref, () => {\n      isControlledRef.current = true;\n      return {\n        startAnimation: () => controls.start('animate'),\n        stopAnimation: () => controls.start('normal'),\n      };\n    });\n\n    const handleMouseEnter = useCallback(\n      (e: React.MouseEvent<HTMLDivElement>) => {\n        if (!isControlledRef.current) controls.start('animate');\n        else onMouseEnter?.(e);\n      },\n      [controls, onMouseEnter]\n    );\n\n    const handleMouseLeave = useCallback(\n      (e: React.MouseEvent<HTMLDivElement>) => {\n        if (!isControlledRef.current) controls.start('normal');\n        else onMouseLeave?.(e);\n      },\n      [controls, onMouseLeave]\n    );\n\n    return (\n      <div\n        className={cn(className)}\n        onMouseEnter={handleMouseEnter}\n        onMouseLeave={handleMouseLeave}\n        {...props}\n      >\n        <motion.svg\n          xmlns=\"http://www.w3.org/2000/svg\"\n          width={size}\n          height={size}\n          viewBox=\"0 0 24 24\"\n          fill=\"none\"\n          overflow=\"visible\"\n          variants={svgVariants}\n          animate={controls}\n          initial=\"normal\"\n        >\n          <path\n            d=\"M12 4V20M20 12H4\"\n            stroke=\"currentColor\"\n            strokeLinecap=\"round\"\n            strokeLinejoin=\"round\"\n            strokeWidth=\"1.5\"\n          />\n        </motion.svg>\n      </div>\n    );\n  }\n);\n\nPlusSignIcon.displayName = 'PlusSignIcon';\n\nexport { PlusSignIcon };\n",
      "type": "registry:ui"
    }
  ],
  "type": "registry:ui"
}